sb_sync/__init__.py
sb_sync/admin.py
sb_sync/apps.py
sb_sync/authentication.py
sb_sync/celery.py
sb_sync/cleanup_sync_logs.py
sb_sync/config.py
sb_sync/error_handling.py
sb_sync/health_check.py
sb_sync/middleware.py
sb_sync/migration_utils.py
sb_sync/models.py
sb_sync/optimizations.py
sb_sync/permissions.py
sb_sync/security.py
sb_sync/serializers.py
sb_sync/tasks.py
sb_sync/test_settings.py
sb_sync/test_urls.py
sb_sync/test_wsgi.py
sb_sync/urls.py
sb_sync/utils.py
sb_sync/views.py
sb_sync/management/__init__.py
sb_sync/management/commands/auto_migrate.py
sb_sync/management/commands/configure_model_discovery.py
sb_sync/management/commands/dynamic_permissions.py
sb_sync/management/commands/manage_config.py
sb_sync/management/commands/optimize_performance.py
sb_sync/management/commands/setup_audit_trails.py
sb_sync/management/commands/setup_organizations.py
sb_sync/management/commands/show_models.py
sb_sync/migrations/0001_initial.py
sb_sync/migrations/__init__.py
sb_sync/templates/sb_sync/audit_trails.html
sb_sync/templates/sb_sync/base.html
sb_sync/templates/sb_sync/config_dashboard.html
sb_sync/templates/sb_sync/model_discovery_config.html
sb_sync/templates/sb_sync/performance_metrics.html
sb_sync/templates/sb_sync/permission_matrix.html
sb_sync/templates/sb_sync/sync_logs.html
sb_sync/templatetags/__init__.py
sb_sync/templatetags/sb_sync_extras.py
sb_sync/tests/__init__.py
sb_sync/tests/test_error_handling.py
sb_sync/tests/test_models.py
sb_sync/tests/test_views.py
sb_sync-2.0.2.dist-info/licenses/LICENSE
test_app/models.py
test_project/__init__.py
test_project/asgi.py
test_project/settings.py
test_project/urls.py
test_project/wsgi.py
sb_sync-2.0.2.dist-info/METADATA
sb_sync-2.0.2.dist-info/WHEEL
sb_sync-2.0.2.dist-info/top_level.txt
sb_sync-2.0.2.dist-info/RECORD
