Metadata-Version: 2.4
Name: sb-sync
Version: 2.0.2
Summary: Django package for data synchronization with PUSH/PULL APIs
Home-page: https://github.com/TheSocialBytes/sync
Author: TheSocialBytes
Author-email: TheSocialBytes <info@thesocialbytes.com>
Maintainer-email: TheSocialBytes <info@thesocialbytes.com>
License: MIT
Project-URL: Homepage, https://github.com/TheSocialBytes/sync
Project-URL: Documentation, https://github.com/TheSocialBytes/sync/blob/main/README.md
Project-URL: Repository, https://github.com/TheSocialBytes/sync
Project-URL: Bug Tracker, https://github.com/TheSocialBytes/sync/issues
Project-URL: Changelog, https://github.com/TheSocialBytes/sync/blob/main/README.md#-changelog
Keywords: django,synchronization,api,multi-tenant,audit-trails
Classifier: Development Status :: 4 - Beta
Classifier: Intended Audience :: Developers
Classifier: License :: OSI Approved :: MIT License
Classifier: Operating System :: OS Independent
Classifier: Programming Language :: Python :: 3
Classifier: Programming Language :: Python :: 3.8
Classifier: Programming Language :: Python :: 3.9
Classifier: Programming Language :: Python :: 3.10
Classifier: Programming Language :: Python :: 3.11
Classifier: Programming Language :: Python :: 3.12
Classifier: Framework :: Django
Classifier: Framework :: Django :: 3.2
Classifier: Framework :: Django :: 4.0
Classifier: Framework :: Django :: 4.1
Classifier: Framework :: Django :: 4.2
Classifier: Framework :: Django :: 5.0
Classifier: Framework :: Django :: 5.1
Classifier: Framework :: Django :: 5.2
Classifier: Topic :: Database
Classifier: Topic :: Internet :: WWW/HTTP :: Dynamic Content
Classifier: Topic :: Software Development :: Libraries :: Python Modules
Classifier: Topic :: System :: Distributed Computing
Classifier: Topic :: System :: Networking
Requires-Python: >=3.8
License-File: LICENSE
Requires-Dist: Django<5.3,>=3.2
Requires-Dist: djangorestframework>=3.14.0
Requires-Dist: PyJWT>=2.6.0
Requires-Dist: python-json-logger>=2.0.4
Requires-Dist: django-cors-headers>=3.13.0
Requires-Dist: celery>=5.2.0
Requires-Dist: redis>=4.0.0
Requires-Dist: bleach>=5.0.0
Requires-Dist: django-filter>=22.0
Requires-Dist: django-cacheops>=7.0.0
Requires-Dist: django-extensions>=3.2.0
Requires-Dist: django-debug-toolbar>=4.0.0
Requires-Dist: django-silk>=5.0.0
Requires-Dist: django-prometheus>=2.3.0
Requires-Dist: prometheus-client>=0.16.0
Requires-Dist: django-simple-history>=3.4.0
Requires-Dist: psutil>=5.9.0
Requires-Dist: requests>=2.28.0
Requires-Dist: urllib3>=1.26.0
Requires-Dist: certifi>=2022.12.7
Requires-Dist: charset-normalizer>=3.0.0
Requires-Dist: idna>=3.4
Requires-Dist: python-dateutil>=2.8.2
Requires-Dist: pytz>=2022.7
Requires-Dist: six>=1.16.0
Requires-Dist: typing-extensions>=4.4.0
Requires-Dist: packaging>=21.3
Requires-Dist: pyparsing>=3.0.9
Requires-Dist: click>=8.1.0
Requires-Dist: kombu>=5.2.0
Requires-Dist: billiard>=3.6.4.0
Requires-Dist: amqp>=5.1.0
Requires-Dist: vine>=5.0.0
Requires-Dist: importlib-metadata>=5.0.0
Requires-Dist: zipp>=3.8.0
Requires-Dist: markupsafe>=2.1.0
Requires-Dist: webencodings>=0.5.1
Requires-Dist: html5lib>=1.1
Requires-Dist: lxml>=4.9.0
Requires-Dist: cssselect>=1.1.0
Requires-Dist: beautifulsoup4>=4.11.0
Requires-Dist: soupsieve>=2.3.0
Provides-Extra: dev
Requires-Dist: pytest>=7.0.0; extra == "dev"
Requires-Dist: pytest-django>=4.5.0; extra == "dev"
Requires-Dist: pytest-cov>=4.0.0; extra == "dev"
Requires-Dist: pytest-mock>=3.10.0; extra == "dev"
Requires-Dist: pytest-xdist>=3.0.0; extra == "dev"
Requires-Dist: pytest-benchmark>=4.0.0; extra == "dev"
Requires-Dist: pytest-html>=3.1.0; extra == "dev"
Requires-Dist: pytest-json-report>=1.5.0; extra == "dev"
Requires-Dist: coverage>=6.5.0; extra == "dev"
Requires-Dist: black>=22.0.0; extra == "dev"
Requires-Dist: isort>=5.10.0; extra == "dev"
Requires-Dist: flake8>=5.0.0; extra == "dev"
Requires-Dist: mypy>=1.0.0; extra == "dev"
Requires-Dist: bandit>=1.7.0; extra == "dev"
Requires-Dist: safety>=2.3.0; extra == "dev"
Requires-Dist: pre-commit>=2.20.0; extra == "dev"
Requires-Dist: tox>=4.0.0; extra == "dev"
Requires-Dist: twine>=4.0.0; extra == "dev"
Requires-Dist: build>=0.10.0; extra == "dev"
Requires-Dist: wheel>=0.38.0; extra == "dev"
Requires-Dist: setuptools>=65.0.0; extra == "dev"
Requires-Dist: pip>=22.0.0; extra == "dev"
Requires-Dist: virtualenv>=20.16.0; extra == "dev"
Requires-Dist: pip-tools>=6.8.0; extra == "dev"
Requires-Dist: pipdeptree>=2.7.0; extra == "dev"
Requires-Dist: pip-audit>=2.4.0; extra == "dev"
Provides-Extra: test
Requires-Dist: pytest>=7.0.0; extra == "test"
Requires-Dist: pytest-django>=4.5.0; extra == "test"
Requires-Dist: pytest-cov>=4.0.0; extra == "test"
Requires-Dist: pytest-mock>=3.10.0; extra == "test"
Requires-Dist: pytest-xdist>=3.0.0; extra == "test"
Requires-Dist: pytest-benchmark>=4.0.0; extra == "test"
Requires-Dist: pytest-html>=3.1.0; extra == "test"
Requires-Dist: pytest-json-report>=1.5.0; extra == "test"
Requires-Dist: coverage>=6.5.0; extra == "test"
Requires-Dist: factory-boy>=3.2.0; extra == "test"
Requires-Dist: faker>=18.0.0; extra == "test"
Requires-Dist: freezegun>=1.2.0; extra == "test"
Requires-Dist: responses>=0.22.0; extra == "test"
Requires-Dist: httpretty>=1.0.0; extra == "test"
Requires-Dist: requests-mock>=1.10.0; extra == "test"
Requires-Dist: betamax>=0.8.0; extra == "test"
Requires-Dist: vcrpy>=5.1.0; extra == "test"
Requires-Dist: pytest-vcr>=1.0.0; extra == "test"
Provides-Extra: docs
Requires-Dist: sphinx>=5.0.0; extra == "docs"
Requires-Dist: sphinx-rtd-theme>=1.0.0; extra == "docs"
Requires-Dist: sphinx-autodoc-typehints>=1.12.0; extra == "docs"
Requires-Dist: sphinx-copybutton>=0.5.0; extra == "docs"
Requires-Dist: sphinx-tabs>=3.0.0; extra == "docs"
Requires-Dist: sphinx-panels>=0.6.0; extra == "docs"
Requires-Dist: sphinx-book-theme>=0.3.0; extra == "docs"
Requires-Dist: myst-parser>=0.18.0; extra == "docs"
Requires-Dist: pydata-sphinx-theme>=0.8.0; extra == "docs"
Requires-Dist: furo>=2022.9.0; extra == "docs"
Requires-Dist: sphinx-design>=0.3.0; extra == "docs"
Requires-Dist: sphinx-autobuild>=2021.3.0; extra == "docs"
Provides-Extra: security
Requires-Dist: bandit>=1.7.0; extra == "security"
Requires-Dist: safety>=2.3.0; extra == "security"
Requires-Dist: pip-audit>=2.4.0; extra == "security"
Provides-Extra: performance
Requires-Dist: django-silk>=5.0.0; extra == "performance"
Requires-Dist: django-debug-toolbar>=4.0.0; extra == "performance"
Requires-Dist: django-extensions>=3.2.0; extra == "performance"
Requires-Dist: django-cacheops>=7.0.0; extra == "performance"
Requires-Dist: django-prometheus>=2.3.0; extra == "performance"
Requires-Dist: prometheus-client>=0.16.0; extra == "performance"
Requires-Dist: psutil>=5.9.0; extra == "performance"
Requires-Dist: memory-profiler>=0.60.0; extra == "performance"
Requires-Dist: line-profiler>=3.5.0; extra == "performance"
Requires-Dist: py-spy>=0.3.0; extra == "performance"
Requires-Dist: pyinstrument>=4.0.0; extra == "performance"
Requires-Dist: scalene>=1.5.0; extra == "performance"
Requires-Dist: fil>=0.0.3; extra == "performance"
Requires-Dist: pytest-benchmark>=4.0.0; extra == "performance"
Requires-Dist: pytest-profiling>=1.7.0; extra == "performance"
Provides-Extra: monitoring
Requires-Dist: django-prometheus>=2.3.0; extra == "monitoring"
Requires-Dist: prometheus-client>=0.16.0; extra == "monitoring"
Requires-Dist: django-silk>=5.0.0; extra == "monitoring"
Requires-Dist: django-debug-toolbar>=4.0.0; extra == "monitoring"
Requires-Dist: django-extensions>=3.2.0; extra == "monitoring"
Requires-Dist: django-cacheops>=7.0.0; extra == "monitoring"
Requires-Dist: psutil>=5.9.0; extra == "monitoring"
Requires-Dist: memory-profiler>=0.60.0; extra == "monitoring"
Requires-Dist: line-profiler>=3.5.0; extra == "monitoring"
Requires-Dist: py-spy>=0.3.0; extra == "monitoring"
Requires-Dist: pyinstrument>=4.0.0; extra == "monitoring"
Requires-Dist: scalene>=1.5.0; extra == "monitoring"
Requires-Dist: fil>=0.0.3; extra == "monitoring"
Dynamic: author
Dynamic: home-page
Dynamic: license-file
Dynamic: requires-python
